{"cameraMode":{"drawMode":0,"name":"Shaded","section":"Shading Mode"},"sceneLighting":true,"audioPlay":false,"sceneViewState":{"m_AlwaysRefresh":false,"showFog":true,"showSkybox":true,"showFlares":true,"showImageEffects":true,"showParticleSystems":true,"showVisualEffectGraphs":true,"m_FxEnabled":true},"in2DMode":false,"pivot":{"x":196.61782836914063,"y":0.9568851590156555,"z":344.7516174316406},"rotation":{"x":0.019082462415099145,"y":-0.973619282245636,"z":0.08874480426311493,"w":0.20934845507144929},"size":0.8660253882408142,"orthographic":false}